netsegpol/__init__.py
netsegpol/measures.py
netsegpol-0.1.0.dist-info/licenses/LICENSE
netsegpol-0.1.0.dist-info/METADATA
netsegpol-0.1.0.dist-info/WHEEL
netsegpol-0.1.0.dist-info/top_level.txt
netsegpol-0.1.0.dist-info/RECORD
