Metadata-Version: 2.4
Name: netsegpol
Version: 0.1.0
Summary: Structural polarization and segregation measures for networks.
Author: Onur Tuncay Bal
License: PolyForm Noncommercial 1.0.0
Requires-Python: >=3.9
License-File: LICENSE
Requires-Dist: numpy>=1.22
Provides-Extra: bcc
Requires-Dist: python-igraph>=0.11; extra == "bcc"
Requires-Dist: scipy>=1.10; extra == "bcc"
Dynamic: license-file
